photototext/__init__.py
photototext-0.1.2.dist-info/LICENSE.txt
photototext-0.1.2.dist-info/METADATA
photototext-0.1.2.dist-info/WHEEL
photototext-0.1.2.dist-info/top_level.txt
photototext-0.1.2.dist-info/RECORD
