Metadata-Version: 2.1
Name: photototext
Version: 0.1.2
Summary: This is a module that can turn a picture into a pattern of letters and symbols.
Home-page: https://pypi.org/project/photototext/
Author: peler
Author-email: peler_little_pig@outlook.com
License: UNKNOWN
Platform: UNKNOWN
Classifier: Programming Language :: Python :: 3
Classifier: License :: OSI Approved :: MIT License
Classifier: Operating System :: OS Independent
Requires-Python: >=3.0
